golumn/App.py
golumn/DelimiterChoice.py
golumn/SQLiteGrid.py
golumn/SQLiteImporter.py
golumn/SQLiteTable.py
golumn/Utils.py
golumn/WindowMenu.py
golumn/__init__.py
golumn/__main__.py
golumn/cli.py
golumn/typer.py
golumn/events/__init__.py
golumn/key_bindings/__init__.py
golumn/key_bindings/vim.py
golumn-0.22.3.dist-info/LICENSE.txt
golumn-0.22.3.dist-info/METADATA
golumn-0.22.3.dist-info/WHEEL
golumn-0.22.3.dist-info/entry_points.txt
golumn-0.22.3.dist-info/top_level.txt
golumn-0.22.3.dist-info/RECORD
