Metadata-Version: 2.1
Name: golumn
Version: 0.22.3
Summary: Graphical CSV viewer. `column` with a "g"
Home-page: https://github.com/ddrscott/golumn
Author: Scott Pierce
Author-email: ddrscott@gmail.com
License: MIT
Keywords: csv development desktop wxWidgets
Classifier: Development Status :: 3 - Alpha
Classifier: Environment :: MacOS X :: Cocoa
Classifier: Environment :: Win32 (MS Windows)
Classifier: License :: OSI Approved
Classifier: Operating System :: MacOS :: MacOS X
Classifier: Operating System :: Microsoft :: Windows :: Windows 7
Classifier: Operating System :: Microsoft :: Windows :: Windows 10
Classifier: Operating System :: POSIX
Classifier: Topic :: Software Development :: User Interfaces
Classifier: Topic :: Desktop Environment
Classifier: Intended Audience :: Developers
Classifier: License :: OSI Approved :: MIT License
Classifier: Programming Language :: Python :: 3.6
Classifier: Programming Language :: Python :: Implementation :: CPython
Requires-Python: >=3
License-File: LICENSE.txt
Requires-Dist: wxPython
Requires-Dist: chardet
